kadane_adv/__init__.py
kadane_adv/core.py
kadane_adv-1.1.0.dist-info/METADATA
kadane_adv-1.1.0.dist-info/WHEEL
kadane_adv-1.1.0.dist-info/top_level.txt
kadane_adv-1.1.0.dist-info/RECORD
