Metadata-Version: 2.4
Name: kadane-adv
Version: 1.1.0
Summary: About An advanced Python library implementing Kadane’s Algorithm with support for 1D & 2D arrays, visualization, subarray constraints, and test coverage. Perfect for data analysis, time-series problems, and algorithm enthusiasts.
Home-page: https://github.com/7pk5/kadane-adv
Author: Parimal Kalpande , Krunal Wankhade
Classifier: Programming Language :: Python :: 3
Classifier: License :: OSI Approved :: MIT License
Classifier: Operating System :: OS Independent
Requires-Python: >=3.6
Dynamic: author
Dynamic: classifier
Dynamic: description
Dynamic: description-content-type
Dynamic: home-page
Dynamic: requires-python
Dynamic: summary
